convertcloud/__init__.py
convertcloud/convertcloud.py
convertcloud/converter.py
convertcloud/formats.py
convertcloud-0.1.0.dist-info/DESCRIPTION.rst
convertcloud-0.1.0.dist-info/METADATA
convertcloud-0.1.0.dist-info/RECORD
convertcloud-0.1.0.dist-info/WHEEL
convertcloud-0.1.0.dist-info/entry_points.txt
convertcloud-0.1.0.dist-info/metadata.json
convertcloud-0.1.0.dist-info/top_level.txt
